transformers/VERSION
transformers/__init__.py
transformers/data_transformer.py
ku_transformers-1.0.3.dist-info/WHEEL
ku_transformers-1.0.3.dist-info/METADATA
ku_transformers-1.0.3.dist-info/RECORD
