Metadata-Version: 2.1
Name: ku-transformers
Version: 1.0.3
Summary: Ku exam transformer
Author: Cesar Juarez
Author-email: cesaripn2@gmail.com
Requires-Python: >=3.7,<4.0
Classifier: Programming Language :: Python :: 3
Classifier: Programming Language :: Python :: 3.7
Classifier: Programming Language :: Python :: 3.8
Requires-Dist: pandas (>=1.1.4,<2.0.0)
Requires-Dist: sklearn (>=0.0,<0.1)
